pytest_xdocker/__init__.py
pytest_xdocker/cache.py
pytest_xdocker/command.py
pytest_xdocker/docker.py
pytest_xdocker/fixtures.py
pytest_xdocker/lock.py
pytest_xdocker/network.py
pytest_xdocker/process.py
pytest_xdocker/retry.py
pytest_xdocker/validators.py
pytest_xdocker/xdocker.py
pytest_xdocker-0.2.7.dist-info/LICENSE.rst
pytest_xdocker-0.2.7.dist-info/METADATA
pytest_xdocker-0.2.7.dist-info/WHEEL
pytest_xdocker-0.2.7.dist-info/entry_points.txt
pytest_xdocker-0.2.7.dist-info/RECORD
