Metadata-Version: 2.3
Name: pytest-xdocker
Version: 0.2.7
Summary: Pytest fixture to run docker across test runs.
Author: Marc Tardif
Author-email: marc@interunion.ca
Requires-Python: >=3.10,<4.0
Classifier: Programming Language :: Python :: 3
Classifier: Programming Language :: Python :: 3.10
Classifier: Programming Language :: Python :: 3.11
Classifier: Programming Language :: Python :: 3.12
Classifier: Programming Language :: Python :: 3.13
Requires-Dist: attrs (>=25.3.0,<26.0.0)
Requires-Dist: netifaces2 (>=0.0.22,<1.0.0)
Requires-Dist: psutil (>=6.1.1,<7.0.0)
Requires-Dist: pyhamcrest (>=2.1.0,<3.0.0)
Requires-Dist: pytest (>=9.0.0,<10.0.0)
Requires-Dist: pytest-cache (>=1.0,<2.0)
Requires-Dist: pytest-xprocess (>=1.0.2,<2.0.0)
